changelog_manager/__init__.py
changelog_manager/__main__.py
changelog_manager/_version.py
changelog_manager/utils.py
changelog_manager-1.4.0.dist-info/LICENSE
changelog_manager-1.4.0.dist-info/METADATA
changelog_manager-1.4.0.dist-info/WHEEL
changelog_manager-1.4.0.dist-info/entry_points.txt
changelog_manager-1.4.0.dist-info/top_level.txt
changelog_manager-1.4.0.dist-info/RECORD
