Metadata-Version: 2.1
Name: changelog_manager
Version: 1.4.0
Summary: Easily manage your changelog using this CLI
Home-page: https://github.com/axelfauvel/changelog-manager
Author: Axel FAUVEL
Author-email: axel.fauvel@gmail.com
License: MIT
Project-URL: Documentation, https://pypi.org/project/changelog-manager/#description
Project-URL: Say Thanks!, https://saythanks.io/to/axel.fauvel
Project-URL: Source, https://github.com/axelfauvel/changelog-manager
Project-URL: Tracker, https://github.com/axelfauvel/changelog-manager/issues
Classifier: Development Status :: 4 - Beta
Classifier: Intended Audience :: Developers
Classifier: Topic :: Software Development :: Build Tools
Classifier: License :: OSI Approved :: MIT License
Classifier: Programming Language :: Python :: 3.12
Classifier: Programming Language :: Python :: 3.11
Classifier: Programming Language :: Python :: 3.10
Classifier: Programming Language :: Python :: 3.9
Requires-Python: >=3.7
License-File: LICENSE
Requires-Dist: keepachangelog ==2.0.0
Requires-Dist: click
